[{"accountID":"null","hardwareID":"null","currentRSN":"halsey","rank":"Deathmatcher","information":"Crybaby Friday"},{"accountID":"null","hardwareID":"null","currentRSN":"death tide","rank":"Scammer","information":"Scammer - Evidence in Discord (Humpvees dh prims tort brim)"},{"accountID":"null","hardwareID":"null","currentRSN":"foxdanleave","rank":"Scammer","information":"Scammer - Evidence in Discord"},{"accountID":"null","hardwareID":"null","currentRSN":"ti77it","rank":"Scammer","information":"Scammer - Evidence in Discord"},{"accountID":"null","hardwareID":"null","currentRSN":"JaeKyung","rank":"Scammer","information":"Scammer - Evidence in Discord"},{"accountID":"null","hardwareID":"null","currentRSN":"hawkeye909","rank":"Scammer","information":"Scammer - Evidence in Discord"},{"accountID":"null","hardwareID":"null","currentRSN":"of-penny","rank":"Scammer","information":"Scammer - Evidence in Discord"},{"accountID":"null","hardwareID":"null","currentRSN":"coyote 1698","rank":"Scammer","information":"Scammer - Evidence in Discord"},{"accountID":"null","hardwareID":"null","currentRSN":"plzdontdmme","rank":"Scammer","information":"Scammer - Evidence in Discord"},{"accountID":"null","hardwareID":"null","currentRSN":"meatymose","rank":"Scammer","information":"Scammer - Evidence in Discord"},{"accountID":"null","hardwareID":"null","currentRSN":"ramybe","rank":"Scammer","information":"Scammer - Evidence in Discord"},{"accountID":"null","hardwareID":"null","currentRSN":"doom","rank":"Deathmatcher","information":"Scammer - Evidence in Discord"},{"accountID":"null","hardwareID":"null","currentRSN":"mod mark","rank":"Deathmatcher","information":"Scammer - Evidence in Discord"},{"accountID":"null","hardwareID":"null","currentRSN":"test of rumm","rank":"Scammer","information":"Scammer - Evidence in Discord"},{"accountID":"null","hardwareID":"null","currentRSN":"ll duki l","rank":"Scammer","information":"Scammer - Evidence in Discord"},{"accountID":"null","hardwareID":"null","currentRSN":"dogspec","rank":"Scammer","information":"Scammer - Evidence in Discord (Recoiled in DH Set)"},{"accountID":"null","hardwareID":"null","currentRSN":"BigGirlzOnly","rank":"Scammer","information":"Account Creation"},{"accountID":"null","hardwareID":"null","currentRSN":"SonyRTP","rank":"Scammer","information":"Account Creation"},{"accountID":"null","hardwareID":"null","currentRSN":"wolfrowar","rank":"Scammer","information":"Evidence in Discord"},{"accountID":"null","hardwareID":"null","currentRSN":"getsal","rank":"Scammer","information":"Account Creation"},{"accountID":"null","hardwareID":"null","currentRSN":"XChocolocoX","rank":"Scammer","information":"Account Creation"},{"accountID":"null","hardwareID":"null","currentRSN":"purelybsy","rank":"Scammer","information":"Account Creation"},{"accountID":"null","hardwareID":"null","currentRSN":"MP 25","rank":"Scammer","information":"Account Creation"},{"accountID":"null","hardwareID":"null","currentRSN":"MR CR1M1NAL","rank":"Scammer","information":"Account Creation"},{"accountID":"null","hardwareID":"null","currentRSN":"B L 0 D","rank":"Scammer","information":"Scammed: https://youtu.be/tNa_yF2GGJk"},{"accountID":"null","hardwareID":"null","currentRSN":"AIytus","rank":"Scammer","information":"Account Creation"},{"accountID":"null","hardwareID":"null","currentRSN":"u list M","rank":"Scammer","information":"Account Creation"},{"accountID":"null","hardwareID":"null","currentRSN":"nomi xx","rank":"Scammer","information":"Account Creation"},{"accountID":"null","hardwareID":"null","currentRSN":"adam 1-1ob","rank":"Scammer","information":"Account Creation"},{"accountID":"null","hardwareID":"null","currentRSN":"rodney","rank":"Scammer","information":"Account Creation"},{"accountID":"null","hardwareID":"null","currentRSN":"testing","rank":"Deathmatcher","information":"Account Creation"},{"accountID":"null","hardwareID":"null","currentRSN":"nomi xx","rank":"Scammer","information":"Account Creation"},{"accountID":"null","hardwareID":"null","currentRSN":"SexThenFIex","rank":"Scammer","information":"Account Creation"},{"accountID":"null","hardwareID":"null","currentRSN":"maxspeclnc","rank":"Scammer","information":"Account Creation"},{"accountID":"null","hardwareID":"null","currentRSN":"STEM LEM","rank":"Scammer","information":"Account Creation"},{"accountID":"null","hardwareID":"null","currentRSN":"SellA50","rank":"Scammer","information":"Account Creation"},{"accountID":"null","hardwareID":"null","currentRSN":"handcold","rank":"Scammer","information":"Account Creation"},{"accountID":"null","hardwareID":"null","currentRSN":"Dudos wild","rank":"Scammer","information":"Account Creation"},{"accountID":"null","hardwareID":"null","currentRSN":"Fish SkooI","rank":"Scammer","information":"Account Creation"},{"accountID":"null","hardwareID":"null","currentRSN":"KENSI X","rank":"Scammer","information":"Account Creation"},{"accountID":"null","hardwareID":"null","currentRSN":"DubieDobiess","rank":"Scammer","information":"Account Creation"},{"accountID":"null","hardwareID":"null","currentRSN":"pikinlekuntt","rank":"Scammer","information":"Account Creation"},{"accountID":"null","hardwareID":"null","currentRSN":"Kravan Budz","rank":"Scammer","information":"Account Creation"},{"accountID":"null","hardwareID":"null","currentRSN":"FreeSquirt","rank":"Scammer","information":"Account Creation"},{"accountID":"null","hardwareID":"null","currentRSN":"Pans_7","rank":"Scammer","information":"Account Creation"},{"accountID":"null","hardwareID":"null","currentRSN":"Hullahop","rank":"Scammer","information":"Account Creation"},{"accountID":"null","hardwareID":"null","currentRSN":"Nocolor","rank":"Scammer","information":"Account Creation"},{"accountID":"null","hardwareID":"null","currentRSN":"Tini Tempa","rank":"Scammer","information":"Account Creation"},{"accountID":"null","hardwareID":"null","currentRSN":"MakeItHappe","rank":"Scammer","information":"Account Creation"},{"accountID":"null","hardwareID":"null","currentRSN":"BazzDem","rank":"Scammer","information":"Account Creation"},{"accountID":"null","hardwareID":"null","currentRSN":"p152","rank":"Scammer","information":"Account Creation"},{"accountID":"null","hardwareID":"null","currentRSN":"Chris JS","rank":"Scammer","information":"Account Creation"},{"accountID":"null","hardwareID":"null","currentRSN":"rikku 07","rank":"Scammer","information":"Account Creation"},{"accountID":"null","hardwareID":"null","currentRSN":"mi puente","rank":"Scammer","information":"Account Creation"},{"accountID":"null","hardwareID":"null","currentRSN":"MindFullBird","rank":"Deathmatcher","information":"Account Creation"},{"accountID":"null","hardwareID":"null","currentRSN":"Grab Cabbage","rank":"Deathmatcher","information":"Account Creation"},{"accountID":"null","hardwareID":"null","currentRSN":"Wakereeder","rank":"Scammer","information":"Account Creation"},{"accountID":"null","hardwareID":"null","currentRSN":"baddi cal","rank":"Scammer","information":"Account Creation"},{"accountID":"null","hardwareID":"null","currentRSN":"pack_all","rank":"Scammer","information":"Account Creation"},{"accountID":"null","hardwareID":"null","currentRSN":"ztrs","rank":"Scammer","information":"Account Creation"},{"accountID":"null","hardwareID":"null","currentRSN":"bag and gag","rank":"Scammer","information":"Account Creation"},{"accountID":"null","hardwareID":"null","currentRSN":"Gargantuman","rank":"Scammer","information":"Account Creation"},{"accountID":"null","hardwareID":"null","currentRSN":"o7T","rank":"Scammer","information":"Account Creation"},{"accountID":"null","hardwareID":"null","currentRSN":"NinjaBoss","rank":"Scammer","information":"Account Creation"},{"accountID":"null","hardwareID":"null","currentRSN":"Jamwatchh","rank":"Scammer","information":"Account Creation"},{"accountID":"null","hardwareID":"null","currentRSN":"JBF","rank":"Deathmatcher","information":"Account Creation"},{"accountID":"null","hardwareID":"null","currentRSN":"Proper degen","rank":"Deathmatcher","information":"Account Creation"},{"accountID":"null","hardwareID":"null","currentRSN":"Taxzan","rank":"Deathmatcher","information":"Account Creation"},{"accountID":"null","hardwareID":"null","currentRSN":"Testimony","rank":"Deathmatcher","information":"Account Creation"},{"accountID":"null","hardwareID":"null","currentRSN":"schevetand","rank":"Scammer","information":"Account Creation"},{"accountID":"null","hardwareID":"null","currentRSN":"Zbepix","rank":"Deathmatcher","information":"Account Creation"},{"accountID":"null","hardwareID":"null","currentRSN":"Meriva","rank":"Deathmatcher","information":"Account Creation"},{"accountID":"null","hardwareID":"null","currentRSN":"Butt Job","rank":"Deathmatcher","information":"Account Creation"},{"accountID":"null","hardwareID":"null","currentRSN":"soupnbannock","rank":"Scammer","information":"Account Creation"},{"accountID":"null","hardwareID":"null","currentRSN":"BBQ CHICKEN","rank":"Scammer","information":"Account Creation"},{"accountID":"null","hardwareID":"null","currentRSN":"M dcb","rank":"Scammer","information":"Account Creation"},{"accountID":"null","hardwareID":"null","currentRSN":"Died AgainOK","rank":"Scammer","information":"Account Creation"},{"accountID":"null","hardwareID":"null","currentRSN":"Demco","rank":"Scammer","information":"Account Creation"},{"accountID":"null","hardwareID":"null","currentRSN":"breave lion","rank":"Scammer","information":"Impostering"},{"accountID":"null","hardwareID":"null","currentRSN":"BirGirlzOnly","rank":"Deathmatcher","information":"Account Creation"},{"accountID":"null","hardwareID":"null","currentRSN":"Family Feudz","rank":"Scammer","information":"Account Creation"},{"accountID":"null","hardwareID":"null","currentRSN":"DM DH","rank":"Scammer","information":"Account Creation"},{"accountID":"null","hardwareID":"null","currentRSN":"VKWPSO203DS","rank":"Scammer","information":"Account Creation"},{"accountID":"null","hardwareID":"null","currentRSN":"KILL LMFO","rank":"Scammer","information":"Account Creation"},{"accountID":"null","hardwareID":"null","currentRSN":"darth vorez","rank":"Deathmatcher","information":"Account Creation"},{"accountID":"null","hardwareID":"null","currentRSN":"circle small","rank":"Scammer","information":"Account Creation"},{"accountID":"null","hardwareID":"null","currentRSN":"sx1rtf0","rank":"Scammer","information":"Account Creation"},{"accountID":"null","hardwareID":"null","currentRSN":"nomi xx","rank":"Deathmatcher","information":"Account Creation"},{"accountID":"null","hardwareID":"null","currentRSN":"ATACAME","rank":"Deathmatcher","information":"Account Creation"},{"accountID":"null","hardwareID":"null","currentRSN":"deltegul","rank":"Scammer","information":"Account Creation"},{"accountID":"null","hardwareID":"null","currentRSN":"G00chticfla","rank":"Deathmatcher","information":"Account Creation"},{"accountID":"null","hardwareID":"null","currentRSN":"Dulay","rank":"Scammer","information":"Account Creation"},{"accountID":"null","hardwareID":"null","currentRSN":"Sulaymaniyah","rank":"Scammer","information":"Account Creation"},{"accountID":"null","hardwareID":"null","currentRSN":"Liftn","rank":"Scammer","information":"Account Creation"},{"accountID":"null","hardwareID":"null","currentRSN":"sitamoop","rank":"Scammer","information":"Account Creation"},{"accountID":"null","hardwareID":"null","currentRSN":"Elyesian Pk","rank":"Deathmatcher","information":"Account Creation"},{"accountID":"null","hardwareID":"null","currentRSN":"Elyasian Pk","rank":"Scammer","information":"Account Creation"},{"accountID":"null","hardwareID":"null","currentRSN":"s1dwfkm3","rank":"Deathmatcher","information":"Account Creation"},{"accountID":"null","hardwareID":"null","currentRSN":"Timmeen","rank":"Scammer","information":"Account Creation"},{"accountID":"null","hardwareID":"null","currentRSN":"malfor xrp","rank":"Deathmatcher","information":"Account Creation"},{"accountID":"null","hardwareID":"null","currentRSN":"Rip Papi","rank":"Deathmatcher","information":"History: Scammed 2.4b Pot against Papa Sher (paid back)"},{"accountID":"null","hardwareID":"null","currentRSN":"Dabe Sucks","rank":"Deathmatcher","information":"Account Creation"},{"accountID":"null","hardwareID":"null","currentRSN":"kbd lord420","rank":"Friend","information":"Friend [1B Max] purchased"},{"accountID":"null","hardwareID":"null","currentRSN":"Put It Here","rank":"Lieutenant","information":"<:lieutenant:1129516066406666380> [25B Max] purchased"},{"accountID":"null","hardwareID":"null","currentRSN":"3aws","rank":"Friend","information":"Friend [1B Max] purchased"},{"accountID":"null","hardwareID":"null","currentRSN":"MilanOnKick","rank":"Deathmatcher","information":"Account Creation"},{"accountID":"null","hardwareID":"null","currentRSN":"AF1","rank":"Deathmatcher","information":"Account Creation"},{"accountID":"null","hardwareID":"null","currentRSN":"Blue Bicycle","rank":"Friend","information":"Friend [1B Max] purchased"},{"accountID":"null","hardwareID":"null","currentRSN":"anom1111","rank":"Corporal","information":"Corporal [5B Max] purchased"},{"accountID":"null","hardwareID":"null","currentRSN":"Adam 1-10B","rank":"General","information":"General [100B Max] purchased"}]